pi_usb_gadget_controller/UsbGadgetController.py
pi_usb_gadget_controller/UsbGadgetRestServer.py
pi_usb_gadget_controller/UsbGadgetSocketServer.py
pi_usb_gadget_controller/__init__.py
pi_usb_gadget_controller/__main__.py
pi_usb_gadget_controller/gadget_device.py
pi_usb_gadget_controller/html.py
pi_usb_gadget_controller/keys.py
pi_usb_gadget_controller/send_key.py
pi_usb_gadget_controller/protocols/UsbHidBaseProtocol.py
pi_usb_gadget_controller/protocols/UsbHidProtocolV1.py
pi_usb_gadget_controller/protocols/UsbHidProtocolV2.py
pi_usb_gadget_controller/protocols/__init__.py
pi_usb_gadget_controller-0.4.0.dist-info/LICENSE
pi_usb_gadget_controller-0.4.0.dist-info/METADATA
pi_usb_gadget_controller-0.4.0.dist-info/WHEEL
pi_usb_gadget_controller-0.4.0.dist-info/entry_points.txt
pi_usb_gadget_controller-0.4.0.dist-info/top_level.txt
pi_usb_gadget_controller-0.4.0.dist-info/RECORD
