Metadata-Version: 2.1
Name: pi_usb_gadget_controller
Version: 0.4.0
Summary: Application to take commands and send via USB to a Media device like a FireTV or Andriod TV with ChromeCast
Home-page: https://github.com/designer-living/pi-usb-gadget-controller
Download-URL: https://github.com/designer-living/pi-usb-gadget-controller/0.4.0.tar.gz
Author: Foxy82
Author-email: foxy82.github@gmail.com
License: Apache 2.0
Classifier: Development Status :: 3 - Alpha
Classifier: Intended Audience :: Developers
Classifier: Topic :: Software Development :: Libraries :: Python Modules
Classifier: License :: OSI Approved :: Apache Software License
Classifier: Operating System :: POSIX :: Linux
Classifier: Programming Language :: Python :: 3
Classifier: Programming Language :: Python :: 3.8
Classifier: Programming Language :: Python :: 3.9
Classifier: Programming Language :: Python :: 3.10
License-File: LICENSE
Requires-Dist: aiohttp
